gnnepcsaft_mcp_server/__init__.py
gnnepcsaft_mcp_server/mcp_server.py
gnnepcsaft_mcp_server/models/.gitignore
gnnepcsaft_mcp_server/models/assoc_8.onnx
gnnepcsaft_mcp_server/models/msigmae_7.onnx
gnnepcsaft_mcp_server/plot_utils.py
gnnepcsaft_mcp_server/utils.py
gnnepcsaft_mcp_server-0.4.0.dist-info/METADATA
gnnepcsaft_mcp_server-0.4.0.dist-info/WHEEL
gnnepcsaft_mcp_server-0.4.0.dist-info/entry_points.txt
gnnepcsaft_mcp_server-0.4.0.dist-info/RECORD
