Metadata-Version: 2.4
Name: gnnepcsaft-mcp-server
Version: 0.4.0
Summary: Model Context Protocol server for GNNPCSAFT tools
License: GNU General Public License v3.0
Author: wildsonbbl
Author-email: wil_bbl@hotmail.com
Requires-Python: >=3.10
Classifier: License :: Other/Proprietary License
Classifier: Programming Language :: Python :: 3
Classifier: Programming Language :: Python :: 3.10
Classifier: Programming Language :: Python :: 3.11
Classifier: Programming Language :: Python :: 3.12
Classifier: Programming Language :: Python :: 3.13
Classifier: Programming Language :: Python :: 3.14
Requires-Dist: feos (>=0.8.0,<0.9.0)
Requires-Dist: gnnepcsaft (>=0.3)
Requires-Dist: mcp (>=1.6.0,<2.0.0)
Requires-Dist: numpy (>=2.2.4,<3.0.0)
Requires-Dist: onnxruntime (>=1.21.0,<2.0.0)
Requires-Dist: rdkit (>=2024.9.6,<2025.0.0)
Requires-Dist: si-units (>=0.11.0,<0.12.0)
